CuckooAPI/__init__.py
cuckoo_api-20170924.1.dist-info/DESCRIPTION.rst
cuckoo_api-20170924.1.dist-info/METADATA
cuckoo_api-20170924.1.dist-info/RECORD
cuckoo_api-20170924.1.dist-info/WHEEL
cuckoo_api-20170924.1.dist-info/metadata.json
cuckoo_api-20170924.1.dist-info/top_level.txt
