Metadata-Version: 2.0
Name: cuckoo-api
Version: 20170924.1
Summary: A Python library to interface with a Cuckoo instance
Home-page: https://github.com/keithjjones/cuckoo-api
Author: Keith J. Jones
Author-email: keith@keithjjones.com
License: LICENSE
Platform: UNKNOWN
Requires-Dist: requests[security]
